lib_test/__init__.py
lib_test/test.py
lib_test/test1/__init__.py
lib_test/test1/test1.py
test279-0.3.0.dist-info/METADATA
test279-0.3.0.dist-info/WHEEL
test279-0.3.0.dist-info/top_level.txt
test279-0.3.0.dist-info/RECORD
